{
    "id": "0587100005c10000",
    "name": "Sub Battle Simulator Preview Promo [C64]",
    "size": 10616451,
    "releaseDate": 20210401,
    "description": "<p>Totally Accurate Battle Simulator is a wacky physics-based tactics game.<br />\nExperience accurate warfare through the ages. From medieval peasants to modern-day advanced weaponry, TABS uses state of the art physics-based simulation to provide you with never-before-seen insight to our greatest battles of history.<br />\n- &quot;This doesn&#39;t look like real history at all&quot;<br />\n- &quot;At least the helmets look correct&quot;<br />\n- &quot;What are you doing in my office? GET OUT&quot;</p>"
}