{
    "description": "「極致音效&資料包」\n・極致音效&資料包\n動畫歌曲與音效：31首、原創BGM：15首、設定資料：54頁\n※音樂為遊戲長度。\n\n【收錄歌曲一覽】\nCom Battler V No Theme\nTobe! GUNDAM\nAi Senshi\nSassoutaru Char\nMobile Suit Sen -Kosen-\nBeyond The Time ~Möbius no Sora wo Koete~\nSTAND UP TO THE VICTORY\nDON'T STOP! CARRY ON!\nVigilante\nnarrative\nL-GAIM -Time for L-GAIM-\nKaze no No Reply\nHEART TO HEART\nYusyaou Tanjo! -Mythology Version-\nYusyaou Tanjo! -Juvenile Version-\nChin -requiem-juvenile- Togi\nRevive\nHEATS\nCan’t Stop\nMAZINGER Z (INFINITY Version)\nOre wa Great Mazinger\nMazinkaiser\nYuzurenai Negai\nHikari to Kage wo Dakishimeta Mama\nGUN×SWORD\nEl Dorado V\nWatashi wa Souzou Suru\nPROMPT\nHello! My World!!\nUNION\nYume no Hero\nZEUTH\nZEXIS\nZ-BLUE\nAmakakeyo Senshi tachi\nExCross\nTora no O o Fume!\nANGER INVERSION\nRaise the anchor!\nWith All Might\nShori to Asu o Kasanete\nMAXIMUM BREAK!!\nVARIABLE FORMATION\nEVERYWHERE YOU GO\nAi to Kiseki no \"\"Umasugi WAVE\"\"\nConcerto of SRW\n\n・特典任務「購買極致音效&資料包」\n※可獲得強化零件：「拓樸瞄準器」；CREDIT：100,000、PP：1,000、MxP：5,000。\n\n※本內容同時內含於同捆遊戲本體、季票、獎勵任務包、極致音效&資料包的「數位終極版」之中。請避免重複購買。",
    "id": "0100ECB0129BF011",
    "name": "極致音效&資料包",
    "publisher": "BANDAI NAMCO Entertainment",
    "releaseDate": 20211028,
    "version": 0
}