{
    "description": "The Succubus cosmetic pack changes Miriam’s default appearance so she can fight demons in style!  \n\nThis cosmetic includes six unique items that can be equipped as a set or individually. When the entire set is worn, the character HUD will change to a unique appearance made just for this cosmetic. \n\nEach item has its own stats and can be upgraded with crafting.  \n\nIndividual items include:  \n\n*  Scythe (WEAPON)\n\n*  Vampiric Wig (HEAD)\n\n*  Vampiric Skinsuit (BODY)\n\n*  Vampiric Wings (ACCESSORY)\n\n*  Vampiric Choker (SCARF)\n\n*  Dream Steal (SHARD)",
    "id": "0100BF500207D002",
    "name": "Succubus Cosmetic Pack",
    "publisher": "505 Games",
    "releaseDate": 20240516,
    "version": 0
}