{
    "description": "The Easter Island chess set is inspired by the mysterious Moai of Easter Island, Polynesia. These head-like, monolithic chess pieces have been beautifully crafted, bringing the Moai not only to life - but to the chess board.\n\nThis pack contains a chess set only, which can be used in any environment in the game.",
    "id": "0100A5900472F003",
    "name": "Chess Ultra: Easter Island chess set",
    "publisher": "Ripstone Publishing",
    "releaseDate": 20180126,
    "version": 0
}