{
    "description": "You thought you saved humanity already? On the Brink: Mutation DLC brings a fifth, special, highly dangerous and purple, disease to eradicate.\n\nDuring infections, the Mutation will pop up unpredictably and becomes a new disease to fight in contaminated cities. Making the game more challenging than ever before, this disease divides the team’s efforts and will cost them precious time.\n\nYou’ll need to plan ahead and coordinate the whole team to fight the new virus and find a cure for the 5th disease.",
    "id": "0100ADA00AD2F003",
    "name": "Pandemic: On the Brink - Mutation",
    "publisher": "Twin Sails",
    "releaseDate": 20210728,
    "version": 0
}