{
    "id": "05852000008d0000",
    "name": "Bust-A-Move [SNES]",
    "size": 10313959,
    "releaseDate": 19940618,
    "description": "<hr />\n<p>[Warning]<br />\nThis application does not currently support iOS8.</p>\n<hr />\n<p>One of TheAppera.com&#39;s Top 50 games of 2009!<br />\nThe original &quot;Bust-A-Move&quot; (Also known as &quot;Puzzle Bobble&quot;) game is reborn on the iPhone / iPod touch, bursting with bubble-popping fun for both 1 and 2 players!<br />\nFeaturing Story Mode, where you control Bub in an all-new puzzle-solving adventure; VS. Mode, where you and a friend play head-to-head over Bluetooth; and Challenge Mode, where the puzzles never stop!<br />\n<strong>VS. Mode is unavailable on first-generation iPod touch<br />\ndevices due to lack of Bluetooth functionality.<br />\n</strong>iOS 4.3 or higher is required to play Bust-A-Move.</p>\n<hr />\n<h2>How to Play:</h2>\n<p>Clear bubbles from the screen by connecting 3 or more of the same color!<br />\nDon&#39;t let them cross the line at the bottom or it&#39;s game over!</p>\n<hr />\n<p>Choose from 2 different<br />\nways to control the action!</p>\n<hr />\n<p>1) Sling Shot:<br />\nPull the bubble back like a pinball and let her rip!<br />\nA fun, unique way to aim and fire!<br />\n2) Tap Shot:<br />\nTap a direction to launch a bubble!<br />\nSimple controls with an intuitive feel!</p>"
}