{
    "id": "0526900001af0000",
    "name": "Survival Kids [GBC]",
    "size": 10012913,
    "releaseDate": 19990617,
    "description": "<p>Survival Kids, known as Stranded Kids in Europe and Survival Kids: Kotou no Boukensha (\"Adventurer of the Solitary Island\") in Japan, is a Game Boy Color game developed by Konami that was released in 1999. The gameplay revolves around surviving on a deserted island. The game features an open-ended structure that presents the player with multiple ways to progress through the game, all at the player's own pace.</p>"
}