{
    "id": "0510300005e90000",
    "name": "Nickelodeon SpongeBob's Truth or Square [PSP]",
    "size": 1252961115,
    "releaseDate": 20091026,
    "description": "<p>SpongeBob SquarePants has gotten himself into quite a predicament. After<br />\nbeing entrusted by Mr. Krabs to keep the Krabby Patty formula safe,<br />\nSpongeBob is overcome with grief for losing the recipe. He then relies<br />\non the help of the most unlikely companion, Plankton, who wants the<br />\nsecret Krabby Patty recipe for himself. With the help of his friends,<br />\nSpongeBob must use Plankton\u2019s memory machine to retrace the happiest<br />\nmoments of his life to find the Krabby Patty formula in time for the<br />\nKrusty Krab\u2019s Eleventy Seventh anniversary.</p>"
}