{
    "id": "0510000001fb0000",
    "name": "Telegraph Crosswords [PSPM]",
    "size": 20444667,
    "releaseDate": 20100601,
    "description": "Play crossword puzzles from Telegraph like you've never played them before!<br/>\n<br/>\r\nWith its handy interface and intuitive controls, this game transfigures the classic pen-and-paper experience.<br/>\n<br/>\r\nFeatures:<br/>\r\n- A whopping 500 puzzles from Telegraph providing many hours of gameplay!<br/>\r\n- Registration of best times in the Hall of Fame.<br/>\r\n- Interactive hints prevent you from being stuck!<br/>\r\n- Autosave as you go: you can stop and resume a puzzle at any time! <br/>\n<br/><br/>\n<br/>\r\nPurchase or use of this item is subject to the PlayStation\u00aeNetwork Terms of Service and User Agreement. If you do not wish to accept all these terms, do not purchase or use this item. This item has been sublicensed to you by Sony Computer Entertainment America. One-time license fee for downloads to up to 2 console systems and 2 portable systems that are associated with the purchasing account."
}