{
    "description": "How many baskets can you score in 40 seconds?\n\nBasketball Arcade is an addictive game designed for real basketball fans of all ages.\n\nFEATURES:\n\n- 4 balls with different scoring rules\n- Bonus round after every 40 points\n- Moving hoop in bonus rounds\n- Easy to pick up one touch swipe controls\n- Realistic physics",
    "id": "010031B01D6FE000",
    "name": "Basketball Arcade",
    "publisher": "IntuitiveComputers",
    "releaseDate": 20231201,
    "version": 0
}