{
    "description": "A story of a repair robot who during the weekend, instead of enjoying his free time watching a speedball game on a planet nearby, has to go to work and fix a malfunction in one of the corporate buildings, as he’s usually the one to be called in such cases.\nBy accident, he discovers a corporate management plot regarding a new project related to the department of power. Unfortunately, the conspirators notice they are being overheard. Toolboy attempts to escape by solving more puzzles, and the more he solves, the more skills as superpowers he gains. Our bot also has an ally in the form of an old computer disconnected from the main system. Toolboy uses special information points to communicate with him and to get more clues.\n\nToolboy is an old-style platform game inspired by the classics, you will find here game mechanisms from such all-time classics games.\nToolboy has 4 superpowers that launch on successive levels\n- Remote control as a Controller\nPower that allows to control some devices by changing their direction of rotation.\n- Cube\nToolboy can turn himself into a cube that looks like an element of scenery, this disguise allows him to\nto hide from drones scanning the area.\n- SpeedRun\nA super run that our Hero uses while speedrunning between levels to escape in from the enemies.\n- Magnetic Walk\nSkill that allows to move large objects, mainly containers, which can be used as climbing and jumping surfaces.",
    "id": "0100B55012216000",
    "name": "Toolboy",
    "publisher": "Art Games Studio",
    "releaseDate": 20201023,
    "version": 0
}