{
    "description": "N-Fusion Interactive's award winning flight-adventure game, Air Mail, has arrived on Nintendo Switch™! Get ready for an incredible ride through a fantasy world filled with exotic lands to explore. \n\nYour adventure begins in the picturesque kingdom of Domeeka, where air mail pilots fly from island to island carrying out tasks for the peaceful villagers. You play the role of Scoop, the youngest pilot to ever join the Domeekan Island Fliers.\n\nBut when conflict erupts it will be up to you to restore peace to the kingdom. Your journey will take you to exciting worlds far from home. And you'll make new friends along the way.\n\n• Campaign mode with 25 missions to complete\n\n• Test your piloting skills in a time attack mode called “Express Delivery”\n\n• Relaxing exploration mode with landmarks and hidden items to discover\n\n• Rich graphical presentation completely remastered for Nintendo Switch™\n\n• Unlock custom paint jobs for your plane\n\n• Illustrated cinematic storytelling\n\n• Sweeping classical score\n\n• Play as a boy or a girl",
    "id": "01004C700B106000",
    "name": "Air Mail",
    "publisher": "N-Fusion",
    "releaseDate": 20180626,
    "version": 0
}