{
    "description": "What is a banana to do when he’s haunted by anxiety and inner demons? Doug’s Nightmare is a cartoony, hand-drawn bullet hell where your job is to help Doug the banana overcome his worst fears by pounding them into oblivion! Part top-down twin-stick shooter and part beat ’em up, Doug’s Nightmare pits you against swarms of bugs, mushrooms, floating brains and more!\n\nDoug can punch when disarmed or pick up a wide variety of weaponry to fend off foes, from slimy squirt guns to spiky clubs. He can don shoes, gloves, cloaks, sunglasses and a wacky wardrobe to improve stats and look stylish as he gains the confidence he’ll need to take on the biggest baddies! Can you guide him to victory?\n\nFeatures:\n\n• Pummel your way through whimsical nightmare scenarios as an anthropomorphic banana!\n• Enjoy comic book style cutscenes and immerse yourself in Doug’s identifiable plight.\n• Use twin-stick controls to dish out damage in beat ’em up style!\n• Fend off swarms of bugs and other weirdly unsettling enemy types.\n• Choose between multiple difficulties to customize the experience.\n• Equip a huge variety of skins and weapons, from bats to squirt guns and more!",
    "id": "01008B601BFD8000",
    "name": "Doug's Nightmare",
    "publisher": "eastasiasoft",
    "releaseDate": 20240522,
    "version": 0
}