{
    "description": "BACKGROUND\nWhile chasing the fortune worthy criminal Lamos on their Alloy Ranger, Space Hunters Kelly and Rambos were trapped by the protective field of the abandoned planet Tanwada. Just as they were struggling to find a way out, robot sisters “No.2” and “No.3” appeared out of nowhere and had asked to join them on their adventure!\nMeanwhile, a mysterious program infected the mechanical army on planet Tanwada and led to their continuous self-evolution.\n\nMAIN FEATURES\n\nClassic 2D Action Platform Levels\nUtilize various movement techniques to conquer the challenging levels; running, jumping, dashing, mid-air dash, wall climbing and double jumps. Use them wisely to track down the wanted criminal; this could be in sunken cities, the freezing Sea of Frost, the endless Abyssal Mines and many more places. Whatever it takes, you will find out the truth and head back with victory!\n\nMultiple Combat Methods\nShooting expert Kelly can shoot different bullets based on the Attribute chip he was equipping. He can also enhance the effect of ammunition through charging! The energy core on his combat uniform can slowly increase the energy needed for special weapons!\nCombat Robot No.2 has more attack methods than you think! Claws, swords, spears and many more, find out what it can do by unlocking various Attribute Chips. It will also collect energy from every hit made on the enemy. Once they have accumulated enough energy, a powerful deathblow will be released based on the Attribute Chip it was equipping. You never know how helpful this could be; it may even turn the situation around!\n\nGigantic Boss Enemies\nMechanical Aircraft, Aggressive Underwater Robots, a Battle Fortress that is digging towards the core of the planet and an enormous Humanoid that was produced in the Machine Arsenal… At the end of each level, there is always a dangerous mutant Machine Boss waiting for you to challenge. Try your best to defeat them in the barrage!\n\nDynamic Pixel Animation\nWith reference to many exquisite pixel art, Super Alloy Ranger seek to strive for details when it comes to this relatively abstract form of art. At the same time, strive to create a world that is more fun and exquisite!\n\nFeatures\nClassic side-scrolling mode of operation, dodge the bullets while jumping, dashing and climbing to progress with the level. · Many hidden pathways are waiting for you to explore.\nBoth characters have many weapons and combat styles up for selection.\nChallenge gigantic boss enemies in dangerous barrages.\nCombining the characteristics of horizontal shooting and horizontal breakthrough. On top of that corresponding combat mechanism is added to the game!\nFun and exquisite pixel animations.",
    "id": "010053E01A7BA000",
    "name": "Super Alloy Ranger",
    "publisher": "Neverland Entertainment",
    "releaseDate": 20230428,
    "version": 0
}