{
    "description": "\"SOLDAM\" is a puzzle game released by JALECO in 1992.\nThe game is an elusive puzzle known only to the fairy folk. The core rule of the game is to line up rows of nuts with the same color horizontally to remove them.\nThe puzzle also has a special trick: surrounding other nuts with a pair of nuts of the same color will turn the nuts in the middle into the other color. Use this to make your way through the game!\n\nThe \"Arcade Archives\" series has faithfully reproduced many classic Arcade masterpieces.\nPlayers can change various game settings such as game difficulty, and also reproduce the atmosphere of arcade display settings at that time. Players can also compete against each other from all over the world with their high scores.\nPlease enjoy the masterpiece that built a generation for video games.\n\n*The options menu and manual are available in Japanese, English, French, German, Italian, and Spanish.",
    "id": "0100E32015798000",
    "name": "Arcade Archives SOLDAM",
    "publisher": "HAMSTER",
    "releaseDate": 20210916,
    "version": 0
}