{
    "description": "Her name is Jack. She has an axe. She is Jack Axe.\nJoin the Jack sisters in a single or multiplayer, 2D open world adventure! Take on a variety of platforming challenges and utilize your axe tossing ability to explore Jack’s unique world. Witness the saga of a young woman breaking taboo by arming herself and taking on a “man’s job,” despite the protestations of an irate god in this Norse/Filipino fusion.\n\n◆ JACK'S FACTS\n• Explore a Norse-Filipino Fantasy Fusion.\n• Take Girl Power To The Next Level (And The Level After That) With Axe Tossing Goodness.\n• Use Jack’s Axe To Perform Incredible Platforming Feats.\n• Play With Up To Four Players In a Campaign and Party Modes.\n• Enjoy a story written by Bari and Melai Silvestre and their 3 imaginative daughters.\n• Prove That Girls Do It Better.",
    "id": "0100EF500EF42000",
    "name": "Jack Axe",
    "publisher": "Neon Doctrine",
    "releaseDate": 20221220,
    "version": 0
}