{
    "description": "◆内なる情熱がぶつかり合うドラマチック推理ミステリー\nフリー記者の歩未と幼馴染の長野が巻き込まれた、名人失踪事件。\nそれは、50年前からの因縁に終止符を打とうとする大勝負の幕開けだった。\n棋士たちの生き様や苦悩、勝負の深遠をドラマチックに描き出す推理ミステリーアドベンチャー。\n現代将棋界を舞台に、様々な思惑が絡み合う濃密なストーリーの幕が開く。\n\n◆主人公・歩未は将棋初心者\nプロ棋士を目指す長野が噛み砕いて教えてくれるので、\n将棋の知識がゼロでも全く問題なし！\nわかりやすい用語集や、将棋が楽しく学べるコーナーもあり、\nプレイ後は自然と将棋に詳しくなれてしまうかも。\n\n◆音楽は岩垂徳行氏描き下ろし。人気棋士も本人役で出演！\nシナリオは数々の物語を生み出した宮下英尚氏（Child-Dream）が担当。\n人気ゲーム作曲家・岩垂徳行氏の心を揺さぶる音楽、総勢11名の声優によるパートボイスにも注目です。\n監修・高橋道雄九段、副監修・香川愛生女流三段に加え、人気棋士が多数出演。\n深いドラマ性で高い評価を受けた原作を大幅に補強し、長編の新シナリオも加え満を持して家庭用ゲーム機向けに登場！\n\n※本作は将棋を題材としたアドベンチャーゲームです。将棋対局プレイはできません。",
    "id": "010020C00DD60000",
    "name": "千里の棋譜 ～現代将棋ミステリー～",
    "publisher": "ケムコ",
    "releaseDate": 20200227,
    "version": 0
}