{
    "description": "Experience the life of a starving artist!\n\nPasspartout puts you into the shoes of a French artist trying to navigate the beautifully confusing art scene. Paint and sell your own art to survive your expensive wine and baguette addiction.\n\n*Paint your own masterpieces! Even you can become the next Van Gogh!\n*Battle with subjectivity and try to charm a variety of self-proclaimed art connoisseurs without losing your \"artistic integrity\"!\n*Survive your wine and baguette bills. Will your addiction to baguettes be your downfall?\n*Unlock fancier galleries and customers!\n*Experience the French art world through a living puppet theater!\n*Includes an amazing soundtrack by our favourite groovin' dinosaurs Synkronosaurus",
    "id": "0100CE600B7B4000",
    "name": "Passpartout: The Starving Artist",
    "publisher": "Flamebait",
    "releaseDate": 20181019,
    "version": 0
}