{
    "description": "「怒首領蜂大往生」は2002年に発売された縦スクロールシューティングゲーム。\nやり込めるゲームシステムや緻密な世界観、挑戦的な難易度が、多くのユーザーの支持を得ました。\n\n今回アーカイブスとして復刻する「怒首領蜂大往生DX」は、同作のフィーチャーフォン移植版。\n「大往生」の名の如く脅威の弾幕に挑むことができるだけではなく、オンラインランキング対応により、全世界のユーザーとスコアを競い合うこともできます。\n\n難易度の変更、自機タイプの選択、強化タイプ(エレメントドール)の選択など腕前や好みに合わせてプレイスタイルを変更できる要素も充実。\nシューティングゲーム初心者も、弾幕熟練者も。死線に挑み、死様を魅せよ。\n\n■ G-MODEアーカイブスとは\n「G-MODEアーカイブス」とは、かつてのフィーチャーフォンアプリゲームを当時のまま忠実に再現しお届けする復刻プロジェクトです。\n\nまた「G-MODEアーカイブス+」は、ジー・モード以外のメーカー・パブリッシャーが開発・配信していたフィーチャーフォンアプリゲームをお届けするブランドです。\n\n・当時のアプリをそのままお楽しみいただけるよう、WEB接続メニューや各種ボタン、キー内容などを移植再現しておりますが、一部機能しないものがあります。\n・Nintendo Switch版の詳しい操作方法については、＋－ボタンを押してPAUSEメニュー内「あそびかた」をご覧ください。\n\n■怒首領蜂大往生DX\n2005年配信　ケイブ作品",
    "id": "010039B014B58000",
    "name": "G-MODEアーカイブス+ 怒首領蜂大往生DX",
    "publisher": "ジー・モード",
    "releaseDate": 20210520,
    "version": 0
}