{
    "description": "故事大綱\n故事發生於並非在第15年即落幕，而是延續到了25年的大正時代。\n少女為了守護沒落衰敗的家族，決心與素未謀面的對象聯姻。\n然而就在此時，少女的弟弟卻手拿一本舊書，原因不明地意圖自焚。\n\n少女陷入一片混亂。\n這時，一個名為【帝國圖書情報資產管理局】，俗稱【鴟鵂】的組織出現在她面前。\n根據對方所述，似乎有一種被稱為【稀有之物】的書籍，會對閱讀之人產生巨大影響。\n而少女也因弟弟自焚，獲得了看見【靈韻】的特殊能力。\n彷彿是命運——要將少女拖入那道火焰之中。\n\n儘管少女感到不知所措，但她最終還是選擇踏出鳥籠，走向外面的世界。\n\n嫉妒、憎恨、侮辱、憐憫───以及，愛。\n\n在前方等待少女的，是充滿背叛、滿佈著妖異氣息的帝都黑暗面。\n少女遭受命運擺佈、歷經擺盪波折，最後她找到的究竟是真相？還是───",
    "id": "0100B88015B0A000",
    "name": "冷然之天秤：帝都幻惑綺譚",
    "publisher": "Game Source Entertainment",
    "releaseDate": 20220120,
    "version": 0
}