{
    "description": "Become a modern Mozart with Piano: Learn and Play, the best piano learning app for Nintendo Switch™.\n\nWell-known and beloved melodies\n\nNursery rhymes or other popular songs make time more enjoyable for children around the world. Sing and play with family, friends or at school.\n\nA marvel of modernity\n\nA small, handy musical instrument that you can take anywhere you want. Relax and immerse yourself in the sounds.\n\nA magical experience\n\nMusic develops memory, motor skills and improves concentration. With its total power, you will awaken your child's creativity and sensitivity to beauty.\n\n\nKey Features:\n- 8 familiar, simple songs\n- free play mode\n- learning mode\n- mini arcade piano game\n- different tempo",
    "id": "010038501A6B8000",
    "name": "Piano: Learn and Play",
    "publisher": "RedDeer.Games",
    "releaseDate": 20230217,
    "version": 0
}