{
    "description": "Do you want to do something meaningful in your life? Do you desire more responsibility like responsibility for the fate of the multiverse hanging in the balance? You might want to consider a career with Godly Corp, an upcoming over-the-top simulator with a focus on woobly tentacle physics! Rest assured that every mistake will bring tremendous consequences, just as you wanted!\n \nThere also won't be time for you to burn out in this job as EVERY day is a completely new challenge. On Monday you will be fighting bug infestation, Tuesdays are usually the days when someone tries to rob us, Wednesday might be the casual day! If these assignments sound too easy to you then we guarantee that the more experienced you are the more interesting challenges you will get! \n \nAs you can see this is a dream job! Add Godly Corp to your Wishlist and sign up today for a better tomorrow!\n \nFeatures:\n- Tentacle Mechanic \n- Every level is something completely different\n- Hilarious humor and presentation\n- Compete on the leaderboard to be the best employee\n- Multitasking hell\n- Twists at every corner\n- Hidden lore bits throughout the whole game\n \n*No healthcare is provided to the employees of Godly Corp",
    "id": "010014900D744000",
    "name": "Godly Corp",
    "publisher": "Ultimate Games",
    "releaseDate": 20190405,
    "version": 0
}