{
    "description": "The early 50s: Joe Dunn, owner of a boxing club, is found dead.\nMeanwhile, rising star Robert Yale, due to take to the ring for the most important fight of his career, has mysteriously disappeared. \nSonia Dunn, Joe’s daughter, takes over the club and must deal with its financial woes. She hires private detective John Blacksad to investigate Yale’s disappearance and to find the missing man. This sinister case will take our investigator to the darkest, most dismal depths of New York.\nWith its anthropomorphic characters and its incredible 1950s feel, BLACKSAD: Under the Skin promises all the eerily dark adventure of a detective novel, just like the eponymous comic book series.\nInvestigations, searches for clues, fights, witness interviews: let your feline instinct guide you as you infiltrate the corrupt world of boxing.\n\n\nFeatures:\n•\tAn official and all-new story for BLACKSAD, set in the comic book series’ unique world, perfectly recreated for gamers.\n\n•\tAn investigative narrative game with gameplay combining investigations, puzzles, quick time events (QTE) and multiple-choice dialog.\n \n•\tMore than 30 characters, including new faces and old favorites, each with their own story and side quests.\n\n•\tAn immersive world with a jazz soundtrack to rival the very best of Hollywood’s film noir.\n\n•\tFans of adventure games will love its gameplay and narration while fans of the comic book series will be thrilled to rediscover the characters and graphic style of this unique world.\n",
    "id": "010032000EA2C000",
    "name": "BLACKSAD: Under the Skin",
    "publisher": "Microids",
    "releaseDate": 20191129,
    "version": 0
}