{
    "description": "謎の天変地異により人類がほぼ死滅し、文明が崩壊してしまった近未来。\n“キーマスター”と呼ばれる人物が支配する\n要塞都市“ダーマタワー”で人々は暮らしていた。\n\n目覚めた主人公は自分が何者でどこから来たのかも分からない。\n与えられた目的はただ一つ。\nこの塔の最上階にいるキーマスターを倒すこと。\n\n高速パルクール×一撃必殺×スタイリッシュアクションで\n最強のサイバーウォーリア―となれ。",
    "id": "0100AAA013598000",
    "name": "Ghostrunner（ゴーストランナー）",
    "publisher": "H2 INTERACTIVE",
    "releaseDate": 20210128,
    "version": 0,
    "category": [
        "アクション"
    ],
    "developer": null,
    "intro": "巨大な要塞都市を駆け抜ける\nサイバーパンク・パルクール・アクション！",
    "isDemo": false,
    "languages": [
        "ja",
        "en",
        "pt",
        "es",
        "fr",
        "de",
        "it",
        "ru"
    ],
    "nsuId": 70010000035466,
    "numberOfPlayers": 1,
    "ratingContent": [
        "暴力"
    ],
    "region": null,
    "rightsId": null,
    "latest_update": {
        "id": "0100AAA013598800",
        "version": "458752"
    }
}