{
    "description": "The battle gong sounds! Make your way through the tournament, aiming for the top!\nThe controls are easy! You can bust out flashy moves with just a single button.\nUnleash jump attacks, drops, holds, and specials, carrying them out just how you think of them!\nUp to 6 players can play. Compete in intense battles with players from all around the world!\nCombine your favorite parts and moves to create your very own custom wrestler!\n\nGrand Slam:\nOne tournament, made up of four stages.\nVarious modes to enjoy, including 1-on-1 Single Matches, team-based Tag Matches, and Battle Royale, where wrestlers fight to be the last one standing.\nWin your way through 7 tournaments and become Grand Champion!\n\nMultiplayer:\n3 types of multiplayer battles: Shared, Local, and Online.\nFor 2-6 players: You can play with friends and family, or with players around the world!\n\nCustom:\nUse parts and prizes that you've acquired from your Grand Slam stage victories and create your very own custom wrestler!\nIn addition to costume and appearance, you can also set your preferred stats and moves!\n\nTraining:\nLearn each wrestler's moves.\nTrain hard to bust out move after move during your matches!",
    "id": "010056300D21A000",
    "name": "Chiki-Chiki Boxy Pro Wrestling",
    "publisher": "The Pocket Company",
    "releaseDate": 20190627,
    "version": 0
}