{
    "description": "マーメイドの姉妹はあなたの助けが必要です。マーメイドの家であるマーメイドキャッスルが破壊されて、宝が全部奪われてしまいました。だから海に飛び込む時間です！コインを集めて美しい水面下の世界を泳いでみましょう。でもサメに注意してください！\n\nシャーク・ザ・ハンマーが指揮する残酷なサメのギャングはキャッスルを攻撃しました。その結果、マーメイドの家は完全に破られてしまいました。さらにひどいことに宝物が全て盗まれました！あなたの助けで姉妹はキャッスルを元に復元することができます。それにサメをきっぱりと排除できるだろう！\n\nこの目的を実現するために魅力的な植物や野生動物に恵まれている８つの綺麗な水中にある場所を体験します。岩石の海底、金色の砂地、サンゴ礁、古代の廃虚、化石にあふれる暗い洞窟…この真っ青な冒険はきっと思い出に残ります。\n\n泳いで、ダッシュして、コインと宝を集めてみましょう。しかし油断してはいけません。悪賢い魚やカニ、くぎのようなウニ、毒クラゲなどの水生生物に邪魔をさせてしまいます。危険を避けるようにダッシュして、それとも真珠をつかんで敵に投げてみましょう。ある敵はコインを残すので、ぜひ集めましょう！親切な魚を探して、錆びついたイカリと爆弾を避けてください。そして、サメが現れたら隠れなければなりません！\n \nゲームの特徴\n• ３人のキャラクター。いつでもかえることができます！\n• ８つの魅惑的な世界に分かれた３０以上のステージ。\n• １０種類以上の敵と障害物。\n• 若いプレイヤーにも再び戻って遊び続きやすい。\n• マーメイドキャッスルは再建を待っています！ ",
    "id": "010066F01553C000",
    "name": "Mermaid Castle",
    "publisher": "IceTorch",
    "releaseDate": 20210708,
    "version": 0
}