{
    "description": "eSport Manager is a game based on the idea of e-sports competitions, especially the most popular - FPS AND MOBA.\n\nCreate your dream team by selecting the players who suit you the best. Care for their constant development, train, sign advertising contracts and be active in social media. Thousands of fans aren’t going to come to you on their own, you have to work for it.\n\nAchieving success in league matches and winning first place requires continuous training. The whole team needs to obtain skills, not just a single player. Their proper use in a match is the key to victory, even with a stronger opponent.\n\nThe base where the team trains is very important for rapid development and achieving success. Expand it, share new premises and install additional items for use. The players must also train at the gym, play, relax and have meals. All these elements have a direct impact on the games in the league.\n\nBefore league matches conduct sparing with other teams, to prepare the appropriate tactics. In sparing you can test different combinations of Special Skills, select weapons, behavior and observe their impact on the game.\n\nStart in Sponsored Tournaments to gain experience and earn cash prizes.\n\nTo reach the very top there is hard work and loads of matches to play.\n\nGame features:\n- two game modes (FPS, MOBA)\n- 3 leagues in each match mode\n- 48 different teams in each League\n- 40 special skills for each member of the team\n- 20 special skills for each team\n- 25 weapon types\n- 12 types of heroes in MOBA\n- 9 rooms in the team base with the possibility to expand\n- 142 items of equipment to purchase\n- 69 Sponsored Tournaments\n- unlimited number of advertising contracts ",
    "id": "010029C00D768000",
    "name": "ESport Manager",
    "publisher": "Ultimate Games",
    "releaseDate": 20190827,
    "version": 0
}