{
    "description": "\"MAT MANIA EXCITING HOUR\" is a wrestling game released by Technos Japan in 1985.\nPlayers use variety techniques to be the champion.\nEnjoy the challenge of facing five strong wrestlers!\n\nThe \"Arcade Archives\" series has faithfully reproduced many classic Arcade masterpieces.\nPlayers can change various game settings such as game difficulty, and also reproduce the atmosphere of arcade display settings at that time. Players can also compete against each other from all over the world with their high scores.\nPlease enjoy the masterpiece that built a generation for video games.",
    "id": "0100C5B009804000",
    "name": "Arcade Archives MAT MANIA EXCITING HOUR",
    "publisher": "HAMSTER",
    "releaseDate": 20191220,
    "version": 0
}