{
    "id": "0515800001a70000",
    "name": "Dead to Rights [GBA]",
    "size": 13272248,
    "releaseDate": 20020603,
    "description": "<p>Dead to Rights is a third-person action video game produced by Namco USA. It was released in 2002 as a timed exclusive for the Xbox, and releases for the PlayStation 2 and Nintendo GameCube followed thereafter. A year after its console debut, the game was released for Microsoft Windows. It was followed by Dead to Rights II in 2004/2005, Dead to Rights: Reckoning for the PSP, also in 2005, and Dead to Rights: Retribution on the PlayStation 3 and Xbox 360 in 2010.</p>"
}