{
    "id": "01005BD010872800",
    "base_tid": "01005BD010872000",
    "name": "",
    "description": "",
    "publisher": "",
    "developer": "",
    "base_release_date": null,
    "first_update_release_date": 20200617,
    "latest_update_release_date": 20200617,
    "latest_update": {
        "version": "65536",
        "release_date": 20200617
    },
    "versions": {
        "65536": 20200617
    },
    "category": [],
    "intro": "",
    "isDemo": false,
    "languages": [],
    "numberOfPlayers": 0,
    "ratingContent": [],
    "region": null
}